mortgage_calculations/__init__.py
mortgage_calculations/find_sum.py
mortgage_calculations/find_time.py
mortgage_calculations-0.1.1.dist-info/LICENSE
mortgage_calculations-0.1.1.dist-info/METADATA
mortgage_calculations-0.1.1.dist-info/WHEEL
mortgage_calculations-0.1.1.dist-info/top_level.txt
mortgage_calculations-0.1.1.dist-info/RECORD
