Metadata-Version: 2.1
Name: mortgage-calculations
Version: 0.1.1
Summary: A mortgage calculator for repayment periods and initial deposit calculations
Home-page: https://github.com/hornetexxon/mortgage_calculations
Author: Viktor Naumenkov
Author-email: viktornaumenkov6@gmail.com
Classifier: Programming Language :: Python :: 3
Classifier: License :: OSI Approved :: MIT License
Classifier: Operating System :: OS Independent
Requires-Python: >=3.6
License-File: LICENSE
